gotu/__init__.py
gotu/aidss.py
gotu/aidss2.py
gotu/bb.py
gotu/binary.py
gotu/dss.py
gotu/events.py
gotu/gaia.py
gotu/grb.py
gotu/jwst.py
gotu/nanograv.py
gotu/planets.py
gotu/quasar.py
gotu/relativity.py
gotu/sd.py
gotu/spiral.py
gotu/supernova.py
gotu/triangle.py
gotu/wits.py
gotu-0.3.dist-info/METADATA
gotu-0.3.dist-info/WHEEL
gotu-0.3.dist-info/dependency_links.txt
gotu-0.3.dist-info/top_level.txt
gotu-0.3.dist-info/RECORD
