Metadata-Version: 2.1
Name: gotu
Version: 0.3
Summary: The Geometry of the Universe
Home-page: https://github.com/swfiua/gotu
Author: Johnny Gill
Author-email: swfiua@gmail.com
License: GPL 3
Keywords: astropy cosmology
Classifier: Development Status :: 4 - Beta
Classifier: Intended Audience :: Science/Research
Classifier: Programming Language :: Python :: 3.6
Requires-Dist: blume
Requires-Dist: matplotlib
Requires-Dist: astropy
Requires-Dist: astroquery
Requires-Dist: scipy
